clippy/__init__.py
clippy/clip.py
clippy/command_method.py
clippy/command_module.py
clippy/command_param.py
clippy/command_protocols.py
clippy/command_return.py
clippy/common.py
Clippy-0.6.4.dist-info/METADATA
Clippy-0.6.4.dist-info/WHEEL
Clippy-0.6.4.dist-info/entry_points.txt
Clippy-0.6.4.dist-info/license.md
Clippy-0.6.4.dist-info/top_level.txt
Clippy-0.6.4.dist-info/RECORD
