Metadata-Version: 2.1
Name: Clippy
Version: 0.6.4
Summary: Clippy generates command-line interfaces for Python modules.
Home-page: https://github.com/gowithfloat/clippy
Author: Steve Richey
Author-email: srichey@gowithfloat.com
License: UNKNOWN
Platform: UNKNOWN
Classifier: Development Status :: 3 - Alpha
Classifier: Intended Audience :: Developers
Classifier: Programming Language :: Python :: 3.6
Classifier: Programming Language :: Python :: 3.7
Classifier: Programming Language :: Python :: 3.8
Classifier: Environment :: Console
Classifier: License :: OSI Approved :: MIT License
Classifier: Operating System :: OS Independent
Requires-Python: >=3.6
